{"positive_branch_factor": Infinity, "wvec_dim": 100, "step_size_path": 0.01, "params_path": null, "description": "Best performing WordNet model.", "max_steps_single": 40000, "report_wait": 50, "dataset_path": "../data/wordnet/", "path_model": "bilinear", "batch_size": 300, "max_negative_samples_train": 10, "max_negative_samples_eval": 200, "split": "test", "init_scale": 0.1, "glove_path": null, "max_steps_path": 40000, "step_size_single": 0.1, "l2_reg": 0.0001, "type_matching_negs": true, "hidden_dim": 20}